__init__.py
diskoize.py
persistent_map.py
diskoize-0.1.2.dist-info/licenses/LICENSE
diskoize-0.1.2.dist-info/METADATA
diskoize-0.1.2.dist-info/WHEEL
diskoize-0.1.2.dist-info/top_level.txt
diskoize-0.1.2.dist-info/RECORD
