Metadata-Version: 2.4
Name: diskoize
Version: 0.1.2
Summary: A memoize-like decorator that caches to disk.
Author-email: Erik Aas <esraiak@gmail.com>
License: Copyright (c) 2018 The Python Packaging Authority
Project-URL: Homepage, https://github.com/esraiak/diskoize
Project-URL: Issues, https://github.com/esraiak/diskoize/issues
Classifier: Programming Language :: Python :: 3
Classifier: Operating System :: OS Independent
Requires-Python: >=3.8
License-File: LICENSE
Dynamic: license-file
